waiba_hello/__init__.py
waiba_hello/say_hello.py
waiba_hello-0.2.dist-info/METADATA
waiba_hello-0.2.dist-info/WHEEL
waiba_hello-0.2.dist-info/entry_points.txt
waiba_hello-0.2.dist-info/top_level.txt
waiba_hello-0.2.dist-info/RECORD
