Metadata-Version: 2.4
Name: waiba_hello
Version: 0.2
Summary: A simple hello package
Author: waiba
Dynamic: author
Dynamic: description
Dynamic: description-content-type
Dynamic: summary
